newchain_keyfile/__init__.py
newchain_keyfile/keyfile.py
newchain_keyfile-0.2.0.dist-info/LICENSE
newchain_keyfile-0.2.0.dist-info/METADATA
newchain_keyfile-0.2.0.dist-info/WHEEL
newchain_keyfile-0.2.0.dist-info/top_level.txt
newchain_keyfile-0.2.0.dist-info/RECORD
