Metadata-Version: 2.1
Name: newchain-keyfile
Version: 0.2.0
Summary: A library for handling the encrypted keyfiles used to store newchain private keys.
Home-page: https://github.com/newtonproject/newchain-keyfile
Author: Xia Wu
Author-email: xiawu@zeuux.org
License: MIT
Keywords: newchain
Classifier: Development Status :: 2 - Pre-Alpha
Classifier: Intended Audience :: Developers
Classifier: License :: OSI Approved :: MIT License
Classifier: Natural Language :: English
Classifier: Programming Language :: Python :: 3
Classifier: Programming Language :: Python :: 3.7
Classifier: Programming Language :: Python :: 3.8
Classifier: Programming Language :: Python :: 3.9
Classifier: Programming Language :: Python :: 3.10
License-File: LICENSE
Requires-Dist: eth-utils (<3,>=2)
Requires-Dist: newchain-keys (>=0.2.0)
Requires-Dist: pycryptodome (<4,>=3.6.6)
Provides-Extra: dev
Requires-Dist: eth-utils (<3,>=2) ; extra == 'dev'
Requires-Dist: newchain-keys (>=0.2.0) ; extra == 'dev'
Requires-Dist: pycryptodome (<4,>=3.6.6) ; extra == 'dev'
Requires-Dist: bumpversion (<1,>=0.5.3) ; extra == 'dev'
Requires-Dist: wheel ; extra == 'dev'
Requires-Dist: setuptools (>=36.2.0) ; extra == 'dev'
Requires-Dist: pluggy (<2,>=1.0.0) ; extra == 'dev'
Requires-Dist: idna (==2.7) ; extra == 'dev'
Requires-Dist: requests (<3,>=2.20) ; extra == 'dev'
Requires-Dist: tox (>=2.7.0) ; extra == 'dev'
Requires-Dist: twine ; extra == 'dev'
Requires-Dist: pytest (<7,>=6.2.5) ; extra == 'dev'
Requires-Dist: flake8 (==4.0.1) ; extra == 'dev'
Provides-Extra: keyfile
Requires-Dist: eth-utils (<3,>=2) ; extra == 'keyfile'
Requires-Dist: newchain-keys (>=0.2.0) ; extra == 'keyfile'
Requires-Dist: pycryptodome (<4,>=3.6.6) ; extra == 'keyfile'
Provides-Extra: lint
Requires-Dist: flake8 (==4.0.1) ; extra == 'lint'
Provides-Extra: test
Requires-Dist: pytest (<7,>=6.2.5) ; extra == 'test'
